latticeflow/__init__.py
latticeflow/info.py
latticeflow_labelling-0.0.1.dist-info/METADATA
latticeflow_labelling-0.0.1.dist-info/WHEEL
latticeflow_labelling-0.0.1.dist-info/top_level.txt
latticeflow_labelling-0.0.1.dist-info/RECORD
